{
  "item_id": "31512",
  "title": "직종별 실무길잡이 - 용접 및 화염절단 종사자",
  "category": "kosha_opl",
  "industry": "제조업",
  "list_type": "OPS",
  "atcfl_no": "FL00014167374",
  "download_url": "https://portal.kosha.or.kr/api/portal24/bizA/p/files/downloadAtchFile?atcflNo=FL00014167374&atcflSeq=1",
  "reg_date": "20121210",
  "keyword": "직종별, 실무,길잡이,실무길잡이,용접,화염,절단",
  "source": "kosha",
  "url": "https://portal.kosha.or.kr/api/portal24/bizA/p/files/downloadAtchFile?atcflNo=FL00014167374&atcflSeq=1",
  "file_url": "https://portal.kosha.or.kr/api/portal24/bizA/p/files/downloadAtchFile?atcflNo=FL00014167374&atcflSeq=1",
  "content": "2012-교육미디어-994\n안전보건공단홈페이지(http://www.kosha.or.kr)의\n안전보건정보َ\n주제별안전보건자료에서다운로드가능\n발행일: 2012년11월┃\n발행인: 백헌기┃\n발행처: 안전보건공단┃\n주소: 인천광역시부평구무네미길478(구산동)\n전화: 032) 5100-500(대표) ┃\n팩스: 032) 5100-049 ┃\n기획∙구성: 안전보건공단교육미디어실\n집필자: 안전보건공단최용진부장대우┃\n편집디자인: 한양애드TEL. 02)2279-0814\n안전보건공단지역별연락처\n서울지역본부\n02-828-1600\n전화\n기관명\n지역\n서울북부지도원\n02-3783-8300\n서울\n강원지도원\n033-815-1004\n강릉출장소\n033-655-1860\n강원\n안전보건공단본부\n032-510-0500\n산업안전보건연구원\n032-510-0761\n화학물질안전보건센터\n042-869-0300\n산업안전보건교육원\n032-510-0951\n경인지역본부\n032-570-7200\n부천지도원\n경기남부지도원\n경기서부지도원\n032-680-6500\n031-259-7149\n031-481-7599\n경기동부지도원\n031-785-3300\n031-841-4900\n경기북부지도원\n경기\n∙\n인천\n전화\n기관명\n지역\n대구지역본부\n053-609-0500\n경북동부지도원\n경북북부지도원\n054-271-2015\n054-478-8000\n대구\n∙\n경북\n대전지역본부\n042-620-5600\n충남지도원\n충북지도원\n041-570-3400\n043-230-7111\n대전\n∙\n충청\n부산지역본부\n051-520-0510\n울산지도원\n경남지도원\n경남동부지도원\n052-226-0510\n055-269-0510\n055-371-7500\n부산\n∙\n경남\n광주지역본부\n062-949-8700\n전북지도원\n전남동부지도원\n제주지도원\n063-240-8500\n061-689-4900\n064-797-7500\n전라\n∙\n제주\n자료를\n다운받을수\n있는곳\n본자료는용접및화염절단종사자들의산업재해예방을위한재해예방실무길잡이로\n작성되었음을알려드립니다. 용접및화염절단종사자들의기술지원및교육지원등\n재해예방을위해활용하시기바랍니다.\n자료의\n용도\n\n02 - 용접및화염절단종사자를위한실무길잡이\nwww.kosha.or.kr - 03\n위험을보는것이안전의시작입니다\n01┃용접작업중화재∙폭발\n●용접작업중가연성/인화성물질, 기름걸레등에의한폭발또는화재\n●밀폐용기의잔류물질을확인또는제거하지않은상태로용단작업시폭발또는화재\n●폭발위험이있는금속성분진발생또는누적작업장에서용접또는용단작업시폭발\nӋ용접작업전주변의가연성물질제거\nӋ밀폐용기내부물질제거및치환작업\nӋ역화방지기등안전장치부착\nӋ용접불꽃의비산을방지할차폐막설치\n안전대책\n위험을보는것이안전의시작입니다\n●준수해야할관련법령\n- 안전보건규칙제232조(폭발또는화재등의예방)\n- 안전보건규칙제239조(위험물등이있는장소에서화기등의사용금지)\n- 안전보건규칙제242조(화기사용금지)\n※ KOSHA GUIDE G-7-2011(가스용접및절단작업에관한안전가이드)\n※ KOSHA GUIDE F-1-2011(용접, 용단작업시화재예방기술지침)\n02┃용접작업중넘어짐및떨어짐재해\n●용접작업중정리정돈되지않은용접호스등에걸려넘어짐\n●불량작업대에서작업중떨어짐\nӋ작업장정리정돈\nӋ안전한작업대및작업발판사용\nӋ안전모, 안전대등개인보호구착용\n안전대책\n●준수해야할관련법령\n-안전보건규칙제32조(보호구의지급등)\n-안전보건규칙제42조(추락의방지)\n-안전보건규칙제44조(안전대의부착설비등)\n※ KOSHA GUIDE C-58-2012(사다리안전보건작업지침)\n용접및화염절단종사자의특성\n용접및화염절단직종은기계나금속구조물및압력용기등을제작하기위하여\n금속, 비금속재료를용접기, 절단기등으로열이나압력을가하여접합하거나절단\n하는업무를수행하며, 용접및화염절단종사자는동업무를수행하는사람으로써\nӋ남성이대부분을차지하고있으며\nӋ노동집약도가높은수작업으로수행되고있으며\nӋ조선업체, 철골건축업체등위험하고어려운현장작업여건으로인해전형적인\n3D 직종으로분류되고있다.\n용접및화염절단작업은제조업뿐만아니라건설및기타의산업에서도매우\n광범위하게적용되고있으며주요업무내용은다음과같다.\n가. 용접업무\nӋ기계나구조물, 압력용기등을제작하기위하여금속, 비금속재료를용접기\n또는절단기등을이용하여용접하거나절단한다.\n나. 용접부점검및청소업무\nӋ용접전, 후에용접부위의이물질을그라인더등수공구및전동공구를이용\n하여제거한다.\n다. 보수용접\nӋ용접부에대한이상유무를검사하여결함이있는부위에대하여보수용접을\n하거나사용중결함이발생된부위등에대한보수용접을한다.\n라. 기타\nӋ전기를이용한전기용접, 가스를이용한가스용접및가스절단등기계및\n구조물제작과관련한업무를수행한다\n용접및화염절단작업은제조업뿐만아니라건설업등에도매우광범위하게\n적용되고있으며주요재해유형은다음과같다.\nӋ용접작업중화재∙폭발\nӋ용접작업중높은곳에서떨어지거나작업장에서걸려넘어지는재해\nӋ용접작업중발생되는용접흄에의한호흡기질환\nӋ용접작업중감전재해등\n\n04 - 용접및화염절단종사자를위한실무길잡이\nwww.kosha.or.kr - 05\n위험을보는것이안전의시작입니다\n03┃용접작업으로인한호흡기질환\n●장시간용접작업시용접흄과다흡입으로인한호흡기질환\n●용접작업중호흡용보호구착용불량으로인한호흡기질한\n04┃용접작업시화상재해\n●용접작업중불꽃의비산에의한화상\n●보안면, 안전화, 앞치마, 장갑등개인용보호구미착용에의한화상\n05┃용접작업중감전재해\n●용접기충전부의절연미흡및용접홀더의파손으로인한감전\n●교류아크용접기의전격방지기등안전장치미설치에의한감전\n●용접기전원공급선, 홀더배선의피복손상등절연파괴로감전\n06┃용접중질식재해\n●밀폐공간용접작업중산소부족에의한질식\nӋ밀폐공간에서의용접작업시지속적이고충분한환기\nӋ용접작업자호흡용보호구등개인보호구착용\n안전대책\n●준수해야할관련법령\n- 안전보건규칙제32조(보호구의지급등)\n- 안전보건규칙제33조(보호구의관리)\n※ KOSHA GUIDE H-80-2012 (밀폐공간보건작업프로그램시행에관한기술지침)\nӋ충전부덮개부착및절연조치\nӋ전격방지기등안전장치설치\nӋ용접장갑등개인보호구착용\n안전대책\n●준수해야할관련법령\n- 안전보건규칙제32조(보호구의지급등)\n- 안전보건규칙제33조(보호구의관리)\n※ KOSHA GUIDE E-4-2012(아크용접장치의선정및사용에관한기술지침)\nӋ통풍또는환기를위해산소사용금지\nӋ작업전산소농도측정및지속적이고충분한환기실시\nӋ긴급사태대비를위한외부연락장치, 비상탈출장치비치\n안전대책\n●준수해야할관련법령\n- 안전보건규칙제241조(통풍등이충분하지않은장소에서의용접등)\n※ KOSHA GUIDE X-25-2012 (밀폐공간리스크에대비한구조계획수립지침)\nӋ밀폐공간용접작업시지속적이고충분한환기실시\nӋ통풍또는환기를위해산소사용금지\nӋ용접작업장주위에소화기비치\n안전대책\n●준수해야할관련법령\n- 안전보건규칙제239조(위험물등이있는장소에서화기등의사용금지)\n- 안전보건규칙제240조(유류등이있는배관이나용기의용접등)\n- 안전보건규칙제241조(통풍등이충분하지않은장소에서의용접등)\n※ KOSHA GUIDE F-1-2011(용접, 용단작업시화재예방기술지침)\n\n06 - 용접및화염절단종사자를위한실무길잡이\nwww.kosha.or.kr - 07\n산소절단기를이용하여내부에가연성물질이잔류하고\n있었던것으로추정되는밀폐된폐드럼의상판을제거하는\n작업중드럼이폭발\n유류등이있는용기의용단작업시안전조치미흡\n밀폐용기내부물질제거및치환작업\nӋ인화성유류가있을우려가있는드럼등의용기에대하여, 인화성물질을제거하는등폭발이나화재의\n예방을위한조치\n화물차량의적재함덮개설치작업중보강재와철재봉을\n용접하기위해사다리를타고올라가교류아크용접기로\n용접하던중감전\n자동전격방지기미설치\n교류아크용접기외함미접지\n용접기홀더선피복손상\n탱크내부아르곤용접작업을하고자질식재해예방을위한\n목적으로산소를주입한후용접작업중화재발생\n탱크내부공기치환용으로가연성가스인산소사용\n밀폐공간환기실시\nӋ용접작업전밀페공간치환용가스로공기사용\n지속적이고충분한환기실시\nӋ용접작업중주기적인산소농도측정및지속적인환기실시\n탱크내부환기불충분으로인한산소부족\n작업중산소농도미측정\nӋ작업전및작업중유독가스, 산소농도주기적측정\nӋ작업중급기및배기팬지속적으로가동\nӋ긴급사태대비를위한외부연락장치, 비상탈출장치비치\n교류아크용접기자동전격방지기부착\nӋ안전인증을받은자동전격방기기를부착하여사용\n교류아크용접기외함접지\nӋ교류아크용접기외함은감전재해예방을위해접지\n위험을보는것이안전의시작입니다\n선박용블록내부에서용접작업중이던작업자가산소\n부족으로인한질식으로사망",
  "has_text": true,
  "collected_at": "2026-04-22"
}