{
  "item_id": "50446",
  "title": "(스리랑카)크레인 작업 사망사고 유발 고위험요인(SIF)",
  "category": "kosha_opl",
  "industry": "건설업",
  "list_type": "OPS",
  "atcfl_no": "HTR2025091809040944010920",
  "download_url": "https://portal.kosha.or.kr/api/portal24/bizA/p/files/downloadAtchFile?atcflNo=HTR2025091809040944010920&atcflSeq=1",
  "reg_date": "20251002",
  "keyword": "크레인,외국인,스리랑카,고위험요인,SIF",
  "source": "kosha",
  "url": "https://portal.kosha.or.kr/api/portal24/bizA/p/files/downloadAtchFile?atcflNo=HTR2025091809040944010920&atcflSeq=1",
  "file_url": "https://portal.kosha.or.kr/api/portal24/bizA/p/files/downloadAtchFile?atcflNo=HTR2025091809040944010920&atcflSeq=1",
  "content": "ඉහළ අවදානම්\nසාධක\nප්‍රවාහනය කරන භාණ්ඩෙය් සම්පූර්ණචලනය පරීක්ෂාකළහැකි \nස්ථානයක ෙදාඹකරය āයාත්මක කිරීම\nවැඩ සඳහා නායකෙයක්ෙයාදවාසංඥාව අනුව ප්‍රවාහන කාර්යය \nāයාත්මක කිරීම\nSIF\nကာကွယ်ေရး\nလုပ်ေဆာင်ချက်များබර භාණ්ඩ හැසිරවීෙම් වැඩ සැලැස්ෙම් ප්‍රවාහන භාණ්ඩෙය් හැඩය, \nප්‍රමාණය සහ සමතුලිතතාවය පවත්වා ගැනීම සඳහා සුදුසු කඹය \nසවිකිරීෙම් ක්‍රමය* ඇතුළත් කිරීම\n*ලණු ෙදක, ලණු හතර සඳහා වන එසවුම් උපකරණ ආදිය\nSIF\nSerious Injury & Fatality\n스리랑카어\nමරණ අනතුරු ඇති කළ හැකි අධි අවදානම් සහිත වැඩ,\nඅවස්ථාසහ ආපදා ඇති කරනසාධකහඳුන්වයි.\nවැළැක්වීෙම්\nāයාමාර්ග\nමාරාන්තිකඅනතුරුඇතිවන\nසුදුසු කඹය සවිකිරීෙම් ක්‍රම පිළිබඳව පූර්වෙස්වක පුහුණුව සහ \nāයාත්මක කිරීම පිළිබඳ පරීක්ෂාව\nෙදාඹකර \nāයාකරුෙග් දෘශ්‍ය \nපරාසය ෙනාමැති වීම\n15.3 %\nකඹ එල්ලීෙම්\nක්‍රමවල ෙදෝෂ\n11.3%\nෙදාඹකර āයාකරුෙග් දෘශ්‍ය පරාසය ෙනාමැතිවීම\nකඹය සම්බන්ධ වන \nඋපකරණෙය් ඇති \nෙදෝෂ සහිත වීම*\n* ෙගවී යාම, \nෙවනස්වීම, හානිවීම, \nෙවල්ඩින් ෙදෝෂ ආදිය\n12.1 %\nකඹය සම්බන්ධ වන උපකරණෙය් ඇති ෙදෝෂ\nෙදාඹකර ආɻත \nප්‍රධාන කාර්යයන්3\nကာကွယ်ေရး\nလုပ်ေဆာင်ချက်များකඹය සම්බන්ධ වන උපකරණ බැහැර කිරීම (කළමනාකරණය) සඳහා\nප්‍රමිතියක් සකස් කිරීම\nකඹය සම්බන්ධ වන උපකරණෙය් ඇතිවිය හැකි හානි වරින්වර \nපරීක්ෂා කිරීම(හානි වූ යන්ත්‍ර බැහැර කිරීම)\nකඹය සම්බන්ධ වන උපකරණෙය් ඇති ෙදෝෂ \n(ෙගවී යාම, ෙවනස්වීම, හානිවීම, ෙවල්ඩින්ෙදෝෂ ආදිය)\n2025-외국인전담팀-892\nඅවදානම් \nසාධක\nඅවදානම් \nසාධක\nඅවදානම්\nසාධක\nවැළැක්වීෙම්\nāයාමාර්ග\nවැළැක්වීෙම්\nāයාමාර්ග",
  "has_text": true,
  "collected_at": "2026-04-22"
}