{
  "item_id": "50661",
  "title": "(타지키스탄)건설기계 작업 사망사고 유발 고위험요인(SIF)",
  "category": "kosha_opl",
  "industry": "건설업",
  "list_type": "OPS",
  "atcfl_no": "HTR2025091610411873986426",
  "download_url": "https://portal.kosha.or.kr/api/portal24/bizA/p/files/downloadAtchFile?atcflNo=HTR2025091610411873986426&atcflSeq=1",
  "reg_date": "20251002",
  "keyword": "건설기계,외국인,타지키스탄,고위험요인,SIF",
  "source": "kosha",
  "url": "https://portal.kosha.or.kr/api/portal24/bizA/p/files/downloadAtchFile?atcflNo=HTR2025091610411873986426&atcflSeq=1",
  "file_url": "https://portal.kosha.or.kr/api/portal24/bizA/p/files/downloadAtchFile?atcflNo=HTR2025091610411873986426&atcflSeq=1",
  "content": "Нодуруст маҳкам кардани \nқисмҳои васлкунандаи дастгоҳ\n        Релеф* ё сохторҳо \nдар роҳи ҳаракат\n* Нишеби баланд, каҷӣ, ноҳамворӣ дар сатҳ, замини нобехатар ва ғайра.\n       Нагузоштани роҳҳои \nҷудогона барои коргарон \nва техникаи сохтмонӣ\nНодуруст маҳкам кардани қисмҳои васлкунандаи дастгоҳ\nМустаҳкамии васлшавии пинҳои бехатарӣ ва ҳолати васлшавӣ \nқисмҳои пайвасткунанда, яъне сатил, пеш аз оғози кор санҷед\nИстифодаи дастгирии бехатарӣ ё блоки бехатарӣ бо мақсади \nпешгирии фуромадани ногаҳонии бум ва даст\nНагузоштани роҳҳои ҷудогона барои коргарон ва \nтехникаи сохтмонӣ\nҶудо кардани роҳҳои ҳаракаткунанда коргарон ва бахши амалиёти \nмошинҳои сохтмонӣ\nРазмещение роҳбар ё мошини роҳнамо дар ҳолате, ки барои оператор \nтаъмин кардани назорати пурра имконнопазир бошад\nРоҳ* ё сохторҳо дар роҳи ҳаракат \n* Нишеби баланд, каҷӣ, ноҳамворӣ дар сатҳ, замини нобехатар ва ғайра.\nҶойгиркунии дастгоҳ, яъне сатил, чангак ва бел, дар сатҳи замин ё ба \nпасттарин нуқта ҳангоми ҷудошавӣ аз курсии ронанда\nСанҷиши шароити замин ва замин дар ҷойҳои корӣ пешакӣ, \nва насби тормоз ва блоки чарх ҳангоми таваққуф ё истодан\nОмили хатар\nЧораҳои \nпешгирикунанда\nОмили хатар\nЧораҳои \nпешгирикунанда\nОмили хатар\nЧораҳои \nпешгирикунанда\n2025-외국인전담팀-911\nОмилҳои боис ба ҷароҳатҳои \nвазнин ва марг\nКорҳо/вазъиятҳои хатари баланд ва омилҳои садамаовар, \nки метавонанд ба садамаҳои марговар оварда расонанд\nОмилҳои хатари баланд\n3 навъҳои асосии корҳо бо \nтехникаи сохтмонӣ\n타지키스탄어",
  "has_text": true,
  "collected_at": "2026-04-22"
}