{
  "item_id": "33446",
  "title": "[중대재해_화학제품]실리콘 드럼 운반 중 드럼 내부로 빠져 질식",
  "category": "kosha_opl",
  "industry": "제조업",
  "list_type": "OPS",
  "atcfl_no": "FL00014169225",
  "download_url": "https://portal.kosha.or.kr/api/portal24/bizA/p/files/downloadAtchFile?atcflNo=FL00014169225&atcflSeq=1",
  "reg_date": "20131216",
  "keyword": "실리콘, 화학물질, 드럼, 질식,중량물취급",
  "source": "kosha",
  "url": "https://portal.kosha.or.kr/api/portal24/bizA/p/files/downloadAtchFile?atcflNo=FL00014169225&atcflSeq=1",
  "file_url": "https://portal.kosha.or.kr/api/portal24/bizA/p/files/downloadAtchFile?atcflNo=FL00014169225&atcflSeq=1",
  "content": "필름코팅 배합실 내에서 작업자가 200ℓ드럼 내의 실리콘 잔량을 계량한 후 팔레트 위로 옮기던 중 밟고 있던 \n전자저울이 뒤로 밀리면서 몸의 균형을 잃고 드럼통 내부로 머리부터 빠져들어가 실리콘액에 기도가 막혀 질식\n재해발생 원인\n!\n안전작업 방법\n중량물 취급시 작업방법 개선\n- 실리콘 드럼 등 중량물을 운반하거나 취급하는 경우에는 전용 운반\n   용구를 사용하거나 2인 1조로 작업 실시\n작업계획서의 작성 및 작업지휘자 지정\n- 떨어짐, 끼임, 넘어짐 등의 예방대책이 포함된 작업계획서를 \n   작성하고 작업지휘자를 지정하여 작업계획서에 따라 작업을 지휘\n중량물 취급 작업방법 미흡\n※ 실리콘 드럼통(용량 : 200ℓ)에 용액이 약 1/3(50Kg) 정도 있던 상태\n중량물 취급 작업계획서 미작성 및 작업지휘자 미지정\n실리콘 드럼 운반 중 드럼 내부로 빠짐\nTIP\n1\n1\n2013-교육미디어-1331\n제조업\n재해사례\n(실리콘 드럼)\n\n●  산업안전보건기준에 관한 규칙\n    제385조(중량물 취급), 제38조(사전조사 및 작업계획서의 작성 등), 제39조(작업지휘자의 지정)\n만화로 보는 재해사례\n중량물 운반은 전용 운반용구를 사용하세요 !\n실리콘 드럼 운반 중 드럼 내부로 빠짐\n참고법령 및 기준\n法",
  "has_text": true,
  "collected_at": "2026-04-22"
}