{
  "source": "kosha",
  "source_type": "portal_api",
  "doc_category": "kosha_opl",
  "source_id": "31139",
  "title": "[중대재해사례]교반기 작업 중 산소결핍에 의한 질식",
  "title_normalized": "교반기 작업 중 산소결핍에 의한 질식",
  "body_text": "2011-교육미디어-1234\n제조업\n2012-교육미디어-623\n작업 전 산소 및 \n유해가스농도 측정\n밀폐공간 내 \n적정 공기 유지\n밀폐공간 내 적정 공기\n● \u0007산소농도 : 18% 이상 23.5% 미만\n● \u0007탄산가스 : 1.5% 미만\n● \u0007황화수소 : 10ppm 미만인 수준의 공기\n교반기 내부 작업 중 질식\n발생 원인\n● 작업 전 산소·유해가스농도 미측정 \n- \u0007저장탱크 내부에 환기가 이뤄지지 않고 액상효모가 발효를 지속하여 산소농도가 8% 이하 \n수준으로 저하\n● 밀폐공간작업용 개인보호구 미착용\n● 감시인 미배치\n액상효모 저장탱크의 교반기 날개를 교체하기 위해 작업자 2명이 탱크내부에 들어간 후 산소결핍에 의한 \n질식으로 1명 사망, 1명이 부상\n● 산업안전보건기준에 관한 규칙 \n제619조 (밀폐공간 보건작업 프로그램 수립·시행 등), 제620조 (환기 등), 제621조 (인원의 점검)\n제622조 (출입의 금지),  제623조 (연락),  제624조 (사고시의 대피 등)\n제625조 (대피용 기구의 비치), 제626조 (구출 시 송기마스크 등의 사용) \n밀폐공간 작업 전 산소·유해가스 농도\n측정 및 충분한 환기 실시\n- \u0007밀폐공간 내부 작업 중 산소농도 18% \n이상 확보를 위한 지속적 환기 실시\n공기호흡기, 송기마스크 등의 개인보호구 \n지급 및 착용\n안전작업 여부를 확인하기 위한 감시인을 \n탱크 외부에 배치\n1\n2\n3\n준수해야 할 관련 법령\n안전작업\nTIP\n\n만화로 보는 중대재해사례_\n교반기 내부 작업 중 질식\n밀폐공간에 들어갈 때에는 작업 전 산소농도를 측정하세요!",
  "has_text": true,
  "content_length": 776,
  "hazards": [
    "질식",
    "화학물질"
  ],
  "work_types": [
    "밀폐공간",
    "기계정비"
  ],
  "equipment": [],
  "tags": [],
  "url": "https://portal.kosha.or.kr/api/portal24/bizA/p/files/downloadAtchFile?atcflNo=FL00014167008&atcflSeq=1",
  "file_url": "https://portal.kosha.or.kr/api/portal24/bizA/p/files/downloadAtchFile?atcflNo=FL00014167008&atcflSeq=1",
  "pdf_path": "",
  "file_sha256": "",
  "industry": "제조업",
  "published_at": "20121010",
  "collected_at": "2026-04-22",
  "language": "ko",
  "status": "mapped"
}