{
  "source": "kosha",
  "source_type": "portal_api",
  "doc_category": "kosha_opl",
  "source_id": "50341",
  "title": "키메세지(15호_크레인)",
  "title_normalized": "키메세지(15호_크레인)",
  "body_text": "OPS\n포스터\nVR\n[기준규칙] 크레인안전조치\n고위험요인-크레인작업\n사고사례<천장크레인편>\n2025-교육혁신실-552\n중량물인양시떨어짐방지를위해\n무게와형태에맞는결속방법·지지점선정\n인양중인중량물이작업자머리위로\n통과하지않도록조치\n크레인해체작업시정해진작업순서에\n따라안전하게실시\n크레인\n(‘25.7.21.) 경남창원소재사업장에서천장크레인으로공구함인양중공구함이떨어져맞음<사망1명>\n(‘25.7.9.) 충남서산소재사업장에서이동식크레인해체작업중고정핀에맞고떨어짐<사망1명>\n(‘25.7.1.) 인천소재사업장에서크레인으로작업대운반중작업대에맞음<사망1명>\n주요사고사례\n안전작업방법\n콘텐츠링크\n스마트폰APP\n위기탈출안전보건설치\n안전보건공단\n산업안전포털\n고용노동부\n중대재해사이렌\n안전보건자료실\n검색\n15호\n동영상\n이동식크레인작업재해예방",
  "has_text": false,
  "content_length": 402,
  "hazards": [
    "추락",
    "충돌",
    "중량물",
    "화학물질",
    "비래낙하"
  ],
  "work_types": [
    "양중",
    "해체",
    "운반"
  ],
  "equipment": [
    "크레인",
    "이동식크레인"
  ],
  "tags": [],
  "url": "https://portal.kosha.or.kr/api/portal24/bizA/p/files/downloadAtchFile?atcflNo=HTR2025081410174891406269&atcflSeq=1",
  "file_url": "https://portal.kosha.or.kr/api/portal24/bizA/p/files/downloadAtchFile?atcflNo=HTR2025081410174891406269&atcflSeq=1",
  "pdf_path": "",
  "file_sha256": "",
  "industry": "제조업",
  "published_at": "20250814",
  "collected_at": "2026-04-22",
  "language": "ko",
  "status": "mapped"
}